README.rst
setup.py
libsixel/__init__.py
libsixel/decoder.py
libsixel/encoder.py
libsixel_python.egg-info/PKG-INFO
libsixel_python.egg-info/SOURCES.txt
libsixel_python.egg-info/dependency_links.txt
libsixel_python.egg-info/not-zip-safe
libsixel_python.egg-info/top_level.txt