Metadata-Version: 1.1
Name: libsixel-python
Version: 0.2.0
Summary: libsixel binding for Python
Home-page: https://github.com/saitoha/libsixel
Author: Hayaki Saito
Author-email: saitoha@me.com
License: MIT
Keywords: skk japanese terminal
Platform: UNKNOWN
Classifier: Development Status :: 4 - Beta
Classifier: Topic :: Terminals
Classifier: Environment :: Console
Classifier: Intended Audience :: End Users/Desktop
Classifier: License :: OSI Approved :: MIT License
Classifier: Programming Language :: Python
